alfort/__init__.py
alfort/app.py
alfort/py.typed
alfort/sub.py
alfort/vdom.py
alfort-0.1.9.dist-info/LICENSE
alfort-0.1.9.dist-info/WHEEL
alfort-0.1.9.dist-info/METADATA
alfort-0.1.9.dist-info/RECORD
