Metadata-Version: 2.1
Name: alfort
Version: 0.1.9
Summary: Elm-like interactive application framework for Python
Home-page: https://github.com/ar90n/alfort
License: Apache-2.0
Keywords: declarative-ui,elm-architecture
Author: Masahiro Wada
Author-email: argon.argon.argon@gmail.com
Requires-Python: >=3.10,<4.0
Classifier: License :: OSI Approved :: Apache Software License
Classifier: Programming Language :: Python :: 3
Classifier: Programming Language :: Python :: 3.10
Classifier: Programming Language :: Python :: 3.11
Project-URL: Repository, https://github.com/ar90n/alfort
